templatex/__init__.py
templatex/engine.py
templatex-0.0.2.dist-info/METADATA
templatex-0.0.2.dist-info/WHEEL
templatex-0.0.2.dist-info/licenses/LICENSE
templatex-0.0.2.dist-info/RECORD
