Metadata-Version: 2.1
Name: templatex
Version: 0.0.2
Summary: A jinja2 dialect for latex templating in python.
Project-URL: Homepage, https://github.com/dataset-sh/templatex
Project-URL: Bug Tracker, https://github.com/dataset-sh/templatex/issues
Author-email: Hao Wu <haowu@dataset.sh>
License-Expression: MIT
License-File: LICENSE
Requires-Python: >=3.8
Requires-Dist: jinja2~=3.0.0
